django_server_side_piwik-1.1.1.dist-info/DESCRIPTION.rst
django_server_side_piwik-1.1.1.dist-info/METADATA
django_server_side_piwik-1.1.1.dist-info/RECORD
django_server_side_piwik-1.1.1.dist-info/WHEEL
django_server_side_piwik-1.1.1.dist-info/metadata.json
django_server_side_piwik-1.1.1.dist-info/top_level.txt
sandbox/__init__.py
sandbox/celery.py
sandbox/settings.py
sandbox/urls.py
sandbox/wsgi.py
server_side_piwik/__init__.py
server_side_piwik/middleware.py
server_side_piwik/tasks.py
server_side_piwik/tests.py
