Metadata-Version: 2.0
Name: django-server-side-piwik
Version: 1.1.1
Summary: Send analytics data to piwik using celery
Home-page: https://gitlab.com/burke-software/django-server-side-piwik
Author: David Burke
Author-email: david@burkesoftware.com
License: BSD
Keywords: django piwik
Platform: UNKNOWN
Classifier: Development Status :: 5 - Production/Stable
Classifier: Environment :: Web Environment
Classifier: Framework :: Django
Classifier: Programming Language :: Python
Classifier: Programming Language :: Python :: 3
Classifier: Intended Audience :: Developers
Classifier: Intended Audience :: System Administrators
Classifier: License :: OSI Approved :: BSD License
Requires-Python: >=3.3
Requires-Dist: celery (>=4.1.0)
Requires-Dist: django-ipware
Requires-Dist: piwikapi (>=0.3)
